gemmr/__init__.py
gemmr/_version.py
gemmr/metrics.py
gemmr/model_selection.py
gemmr/plot.py
gemmr/util.py
gemmr/data/__init__.py
gemmr/data/loaders.py
gemmr/data/preprocessing.py
gemmr/datasets/sample_size_lm_cca.csv
gemmr/datasets/sample_size_lm_pls.csv
gemmr/estimators/__init__.py
gemmr/estimators/helpers.py
gemmr/estimators/r_estimators.py
gemmr/estimators/vanilla.py
gemmr/generative_model/__init__.py
gemmr/generative_model/base.py
gemmr/generative_model/other.py
gemmr/sample_analysis/__init__.py
gemmr/sample_analysis/addon.py
gemmr/sample_analysis/analyzers.py
gemmr/sample_analysis/macros.py
gemmr/sample_analysis/postproc.py
gemmr/sample_size/__init__.py
gemmr/sample_size/interpolation.py
gemmr/sample_size/linear_model.py
gemmr/sample_size/univariate_correlations.py
gemmr-0.4.0.dist-info/LICENSE
gemmr-0.4.0.dist-info/METADATA
gemmr-0.4.0.dist-info/WHEEL
gemmr-0.4.0.dist-info/top_level.txt
gemmr-0.4.0.dist-info/zip-safe
gemmr-0.4.0.dist-info/RECORD
