Metadata-Version: 2.1
Name: gemmr
Version: 0.4.0
Summary: Generative Modeling of Multivariate Relationships
Home-page: https://github.com/murraylab/gemmr
Author: Markus Helmer
License: GPLv3
Project-URL: Homepage, https://github.com/murraylab/gemmr
Project-URL: Documentation, https://gemmr.readthedocs.io/en/latest/
Project-URL: Repository, https://github.com/murraylab/gemmr
Classifier: Programming Language :: Python :: 3
Classifier: License :: OSI Approved :: GNU General Public License v3 (GPLv3)
Classifier: Topic :: Scientific/Engineering
Classifier: Intended Audience :: Science/Research
Requires-Python: >=3.6
License-File: LICENSE
Requires-Dist: numpy
Requires-Dist: scipy
Requires-Dist: pandas
Requires-Dist: xarray
Requires-Dist: netcdf4
Requires-Dist: scikit-learn
Requires-Dist: statsmodels
Requires-Dist: joblib
Requires-Dist: tqdm
